<tooltipList>
  <tooltip code="b_PRBAD1">
    <type>BioBrick</type>
    <illustration>tuto_intro-01</illustration>
  </tooltip>
  <tooltip code="b_PRBAD2">
    <type>BioBrick</type>
    <illustration>tuto_intro-01</illustration>
  </tooltip>
  <tooltip code="b_PRBAD3">
    <type>BioBrick</type>
    <illustration>tuto_intro-01</illustration>
  </tooltip>
  <tooltip code="b_PRCONS">
    <type>BioBrick</type>
    <illustration>tuto_intro-01</illustration>
  </tooltip>
  <tooltip code="b_PRGLUC">
    <type>BioBrick</type>
    <illustration>tuto_intro-01</illustration>
  </tooltip>
  <tooltip code="b_PRLACI">
    <type>BioBrick</type>
    <illustration>tuto_intro-01</illustration>
  </tooltip>
  <tooltip code="b_PRLAMB">
    <type>BioBrick</type>
    <illustration>tuto_intro-01</illustration>
  </tooltip>
  <tooltip code="b_PRTETR">
    <type>BioBrick</type>
    <illustration>tuto_intro-01</illustration>
  </tooltip>
  <tooltip code="b_RBS1">
    <type>BioBrick</type>
    <illustration>tuto_intro-01</illustration>
  </tooltip>
  <tooltip code="b_RBS2">
    <type>BioBrick</type>
    <illustration>tuto_intro-01</illustration>
  </tooltip>
  <tooltip code="b_RBS3">
    <type>BioBrick</type>
    <illustration>tuto_intro-01</illustration>
  </tooltip>
  <tooltip code="b_AMPI">
    <type>BioBrick</type>
    <illustration>tuto_intro-01</illustration>
  </tooltip>
  <tooltip code="b_AMPR">
    <type>BioBrick</type>
    <illustration>tuto_intro-01</illustration>
  </tooltip>
  <tooltip code="b_ARAC">
    <type>BioBrick</type>
    <illustration>tuto_intro-01</illustration>
  </tooltip>
  <tooltip code="b_ATC">
    <type>BioBrick</type>
    <illustration>tuto_intro-01</illustration>
  </tooltip>
  <tooltip code="b_FLUO1">
    <type>BioBrick</type>
    <illustration>tuto_intro-01</illustration>
  </tooltip>
  <tooltip code="b_FLUO2">
    <type>BioBrick</type>
    <illustration>tuto_intro-01</illustration>
  </tooltip>
  <tooltip code="b_FLUO3">
    <type>BioBrick</type>
    <illustration>tuto_intro-01</illustration>
  </tooltip>
  <tooltip code="b_FLUO4">
    <type>BioBrick</type>
    <illustration>tuto_intro-01</illustration>
  </tooltip>
  <tooltip code="b_FLUO5">
    <type>BioBrick</type>
    <illustration>tuto_intro-01</illustration>
  </tooltip>
  <tooltip code="b_FLUO6">
    <type>BioBrick</type>
    <illustration>tuto_intro-01</illustration>
  </tooltip>
  <tooltip code="b_IPTG">
    <type>BioBrick</type>
    <illustration>tuto_intro-01</illustration>
  </tooltip>
  <tooltip code="b_LARA">
    <type>BioBrick</type>
    <illustration>tuto_intro-01</illustration>
  </tooltip>
  <tooltip code="b_MOV">
    <type>BioBrick</type>
    <illustration>tuto_intro-01</illustration>
  </tooltip>
  <tooltip code="b_REPR1">
    <type>BioBrick</type>
    <illustration>tuto_intro-01</illustration>
  </tooltip>
  <tooltip code="b_REPR2">
    <type>BioBrick</type>
    <illustration>tuto_intro-01</illustration>
  </tooltip>
  <tooltip code="b_REPR3">
    <type>BioBrick</type>
    <illustration>tuto_intro-01</illustration>
  </tooltip>
  <tooltip code="b_REPR4">
    <type>BioBrick</type>
    <illustration>tuto_intro-01</illustration>
  </tooltip>
  <tooltip code="b_DTER">
    <type>BioBrick</type>
    <illustration>tuto_intro-01</illustration>
  </tooltip>
  <tooltip code="d_PRCONS:RBS3:FLUO1:DTER">
    <type>Device</type>
    <illustration>pic_d_cons-gfp-low</illustration>
  </tooltip>
  <tooltip code="d_PRCONS:RBS2:FLUO1:DTER">
    <type>Device</type>
    <illustration>pic_d_cons-gfp-low</illustration>
  </tooltip>
  <tooltip code="d_PRCONS:RBS1:FLUO1:DTER">
    <type>Device</type>
    <illustration>pic_d_cons-gfp-med</illustration>
  </tooltip>
  <tooltip code="d_PRCONS:RBS3:MOV:DTER">
    <type>Device</type>
    <illustration>pic_d_cons-speed-low</illustration>
  </tooltip>
  <tooltip code="d_PRCONS:RBS2:MOV:DTER">
    <type>Device</type>
    <illustration>pic_d_cons-speed-low</illustration>
  </tooltip>
  <tooltip code="d_PRCONS:RBS1:MOV:DTER">
    <type>Device</type>
    <illustration>pic_d_cons-speed-med</illustration>
  </tooltip>
</tooltipList>